{"9gb": [{"category": "x86_64-bit_Users_(Pre_April_'08)", "filename": "thread_618145_usr_folder_=_9GB.md"}, {"category": "Server_Platforms", "filename": "thread_823969_LVM_with_9x_9gb_drives.md"}, {"category": "General_Help", "filename": "thread_1555211_Recovering_deleted_9gb_7z_file.md"}, {"category": "Absolute_Beginner_Talk", "filename": "thread_427959_9GB_of_logs.md"}, {"category": "Absolute_Beginner_Talk", "filename": "thread_699238_7.10_Installation_takes_over_9GB_of_hard_drive.md"}, {"category": "Multimedia_Software", "filename": "thread_1677713_Can't_Read_9GB_DVDs.md"}, {"category": "Hardware", "filename": "thread_2194375_Ubuntu_just_deleted_9GB_of_ebooks_on_my_Galaxy.md"}], "9gig": [{"category": "Ubuntu_Studio", "filename": "thread_800648_Converting_a_9gig_mkv_file_into_4.4gig_mkv_file.md"}], "9gthardy": [{"category": "FedoraRedHat_and_derivatives", "filename": "thread_807493_Fedora_9&gt;Hardy_Heron.md"}], "9gt": [{"category": "General_Help", "filename": "thread_1454174_&lt;Ctrl&gt;+&lt;Alt&gt;+&lt;0-9&gt;_not_working.md"}]}